pyintervals/__init__.py
pyintervals/constants.py
pyintervals/interval.py
pyintervals/interval_handler.py
pyintervals/py.typed
pyintervals/search.py
pyintervals/time_value_node.py
pyintervals-1.6.2.dist-info/LICENSE
pyintervals-1.6.2.dist-info/METADATA
pyintervals-1.6.2.dist-info/WHEEL
pyintervals-1.6.2.dist-info/RECORD
