Metadata-Version: 2.3
Name: pyintervals
Version: 1.6.2
Summary: Efficient interval operations.
License: MIT
Keywords: interval,timespan
Author: Serkan Kalay
Author-email: serkanosmankalay@gmail.com
Requires-Python: >=3.9,<4.0.0
Classifier: License :: OSI Approved :: MIT License
Classifier: Programming Language :: Python :: 3
Classifier: Programming Language :: Python :: 3.9
Classifier: Programming Language :: Python :: 3.10
Classifier: Programming Language :: Python :: 3.11
Classifier: Programming Language :: Python :: 3.12
Classifier: Programming Language :: Python :: 3.13
Requires-Dist: importlib-metadata (>=1,<5) ; python_version < "3.8"
Requires-Dist: sortedcontainers (>=2.4.0,<3.0.0)
Requires-Dist: sortedcontainers-stubs (>=2.4.2,<3.0.0)
Requires-Dist: twine (>=6.2.0,<7.0.0)
Project-URL: Repository, https://github.com/serkankalay/pyintervals
